CHANGES.txt
COPYRIGHT.txt
LICENSE.txt
MANIFEST.in
README.rst
curl-sample.sh
htaccess
post.html
sample.cfg
sample.ini
setup.cfg
setup.py
test.html
tox.ini
xmlrpc.ini
doc/Makefile
doc/make.bat
doc/source/bugs.rst
doc/source/changes.rst
doc/source/conf.py
doc/source/contents.rst
doc/source/copyright.rst
doc/source/developer_overview.rst
doc/source/docindex.template
doc/source/documentation.rst
doc/source/glossary.rst
doc/source/index.rst
doc/source/install.rst
doc/source/intro.rst
doc/source/license.rst
doc/source/overview.odp
doc/source/overview.png
doc/source/usage.rst
doc/source/user_overview.rst
doc/source/wsgi.rst
doc/source/xmlrpc.rst
doc/source/_static/custom.css
doc/source/api/api_cachemanager.rst
doc/source/api/api_client.rst
doc/source/api/api_convert.rst
doc/source/api/api_htaccess.rst
doc/source/api/api_oooctl.rst
doc/source/api/api_options.rst
doc/source/api/api_overview.rst
doc/source/api/api_processors.rst
doc/source/api/api_testing.rst
doc/source/api/api_wsgi.rst
doc/source/api/api_xmlrpc.rst
src/ulif/__init__.py
src/ulif.openoffice.egg-info/PKG-INFO
src/ulif.openoffice.egg-info/SOURCES.txt
src/ulif.openoffice.egg-info/dependency_links.txt
src/ulif.openoffice.egg-info/entry_points.txt
src/ulif.openoffice.egg-info/namespace_packages.txt
src/ulif.openoffice.egg-info/not-zip-safe
src/ulif.openoffice.egg-info/requires.txt
src/ulif.openoffice.egg-info/top_level.txt
src/ulif/openoffice/__init__.py
src/ulif/openoffice/cachemanager.py
src/ulif/openoffice/client.py
src/ulif/openoffice/convert.py
src/ulif/openoffice/helpers.py
src/ulif/openoffice/htaccess.py
src/ulif/openoffice/oooctl.py
src/ulif/openoffice/options.py
src/ulif/openoffice/processor.py
src/ulif/openoffice/testing.py
src/ulif/openoffice/wsgi.py
src/ulif/openoffice/xmlrpc.py
src/ulif/openoffice/templates/form_new.tpl
tests/fake_unoconv
tests/test_cachemanager.py
tests/test_client.py
tests/test_convert.py
tests/test_helpers.py
tests/test_htaccess.py
tests/test_oooctl.py
tests/test_options.py
tests/test_processor.py
tests/test_wsgi.py
tests/test_xmlrpc.py
tests/input/image_sample.html
tests/input/image_sample.odt
tests/input/image_sample_html_m20918026.gif
tests/input/sample.ott
tests/input/sample1.css
tests/input/sample1.html
tests/input/sample1.ini
tests/input/sample1.zip
tests/input/sample2.html
tests/input/sample2.ini
tests/input/sample2.zip
