Metadata-Version: 1.1
Name: ulif.openoffice
Version: 1.1.1
Summary: Run OpenOffice as web service.
Home-page: http://pypi.python.org/pypi/ulif.openoffice
Author: Uli Fouquet
Author-email: uli at gnufix.de
License: GPL
Keywords: openoffice pyuno uno openoffice.org libreoffice
Platform: UNKNOWN
Classifier: Development Status :: 3 - Alpha
Classifier: License :: OSI Approved :: GNU General Public License (GPL)
Classifier: Programming Language :: Python
Classifier: Programming Language :: Python :: 2 :: Only
Classifier: Programming Language :: Python :: 2.6
Classifier: Programming Language :: Python :: 2.7
Classifier: Operating System :: POSIX
Classifier: Framework :: Paste
Classifier: Environment :: Web Environment
Classifier: Topic :: Software Development :: Libraries :: Python Modules
Classifier: Topic :: Internet :: WWW/HTTP
Classifier: Topic :: Internet :: WWW/HTTP :: WSGI
Classifier: Topic :: Internet :: WWW/HTTP :: WSGI :: Application
Classifier: Topic :: Internet :: WWW/HTTP :: WSGI :: Middleware
Classifier: Topic :: Office/Business :: Office Suites
